ebs/__init__.py
ebs/modbus/__init__.py
ebs/modbus/_version.py
ebs/modbus/client.py
ebs/modbus/decoder.py
ebs/modbus/device.py
ebs/modbus/hotplug.py
ebs/modbus/mei.py
ebs_modbus-1.2.0.dist-info/LICENSE.txt
ebs_modbus-1.2.0.dist-info/METADATA
ebs_modbus-1.2.0.dist-info/RECORD
ebs_modbus-1.2.0.dist-info/WHEEL
ebs_modbus-1.2.0.dist-info/top_level.txt
